causalipy/custom_types.py
causalipy/did/doubly_robust.py
causalipy/did/multi_periods.py
causalipy/logistic_regression.py
causalipy/ols.py
causalipy-0.1.1.dist-info/LICENSE
causalipy-0.1.1.dist-info/WHEEL
causalipy-0.1.1.dist-info/METADATA
causalipy-0.1.1.dist-info/RECORD
