Metadata-Version: 2.1
Name: causalipy
Version: 0.1.1
Summary: Causal Methods Implemented in Python
Home-page: https://github.com/mohelm/causalipy
License: MIT
Author: Moritz Helm
Author-email: mohelm84@gmail.com
Requires-Python: >=3.9,<3.11
Classifier: License :: OSI Approved :: MIT License
Classifier: Programming Language :: Python :: 3
Classifier: Programming Language :: Python :: 3.10
Classifier: Programming Language :: Python :: 3.9
Requires-Dist: matplotlib (>=3.5.0,<4.0.0)
Requires-Dist: pandas (>=1.3.4,<2.0.0)
Requires-Dist: patsy (>=0.5.2,<0.6.0)
Requires-Dist: scipy (>=1.7.2,<2.0.0)
Project-URL: Repository, https://github.com/mohelm/causalipy
